MANIFEST.in
README.txt
setup.cfg
setup.py
c2/__init__.py
c2.app.shortnameselection.egg-info/PKG-INFO
c2.app.shortnameselection.egg-info/SOURCES.txt
c2.app.shortnameselection.egg-info/dependency_links.txt
c2.app.shortnameselection.egg-info/entry_points.txt
c2.app.shortnameselection.egg-info/namespace_packages.txt
c2.app.shortnameselection.egg-info/not-zip-safe
c2.app.shortnameselection.egg-info/requires.txt
c2.app.shortnameselection.egg-info/top_level.txt
c2/app/__init__.py
c2/app/shortnameselection/__init__.py
c2/app/shortnameselection/base.py
c2/app/shortnameselection/configure.zcml
c2/app/shortnameselection/tests.py
c2/app/shortnameselection/version.txt
docs/HISTORY.txt
docs/INSTALL.txt
docs/LICENSE.GPL
docs/LICENSE.txt