Metadata-Version: 1.0
Name: c2.app.shortnameselection
Version: 1.0a2
Summary: This product is set of tools that create various types of shortname for Plone
Home-page: http://www.cmscom.jp
Author: CMScom
Author-email: terada@cmscom.jp
License: GPL
Keywords: shortname selection japanese plone
Platform: UNKNOWN
Classifier: Framework :: Plone
Classifier: Programming Language :: Python
Classifier: Topic :: Software Development :: Libraries :: Python Modules
